ksv/__init__.py
ksv/cli.py
ksv/ksv.py
ksv-0.1.7.dist-info/AUTHORS.rst
ksv-0.1.7.dist-info/LICENSE
ksv-0.1.7.dist-info/METADATA
ksv-0.1.7.dist-info/WHEEL
ksv-0.1.7.dist-info/entry_points.txt
ksv-0.1.7.dist-info/top_level.txt
ksv-0.1.7.dist-info/RECORD
