Metadata-Version: 2.1
Name: ksv
Version: 0.1.7
Summary: ksv decodes/encodes entire Kubernetes secrets files
Home-page: https://github.com/metadave/ksv
Author: Dave Parfitt
Author-email: dparfitt@mozilla.com
License: Apache Software License 2.0
Keywords: ksv
Platform: UNKNOWN
Classifier: Development Status :: 2 - Pre-Alpha
Classifier: Intended Audience :: Developers
Classifier: License :: OSI Approved :: Apache Software License
Classifier: Natural Language :: English
Classifier: Programming Language :: Python :: 3
Classifier: Programming Language :: Python :: 3.4
Classifier: Programming Language :: Python :: 3.5
Classifier: Programming Language :: Python :: 3.7
Requires-Dist: Click (>=6.0)
Requires-Dist: pyyaml
